pytest_commander/__init__.py
pytest_commander/__main__.py
pytest_commander/api.py
pytest_commander/environment.py
pytest_commander/eventlet_utils.py
pytest_commander/nodeid.py
pytest_commander/plugin.py
pytest_commander/result_tree.py
pytest_commander/runner.py
pytest_commander/watcher.py
pytest_commander/web_client/build/asset-manifest.json
pytest_commander/web_client/build/favicon.png
pytest_commander/web_client/build/index.html
pytest_commander/web_client/build/manifest.json
pytest_commander/web_client/build/robots.txt
pytest_commander/web_client/build/static/css/2.73420eac.chunk.css
pytest_commander/web_client/build/static/css/2.73420eac.chunk.css.map
pytest_commander/web_client/build/static/js/2.ae4218b3.chunk.js
pytest_commander/web_client/build/static/js/2.ae4218b3.chunk.js.LICENSE.txt
pytest_commander/web_client/build/static/js/2.ae4218b3.chunk.js.map
pytest_commander/web_client/build/static/js/main.e936a9fa.chunk.js
pytest_commander/web_client/build/static/js/main.e936a9fa.chunk.js.map
pytest_commander/web_client/build/static/js/runtime-main.0dccac06.js
pytest_commander/web_client/build/static/js/runtime-main.0dccac06.js.map
bms_webui-0.0.4.dist-info/LICENSE
bms_webui-0.0.4.dist-info/METADATA
bms_webui-0.0.4.dist-info/WHEEL
bms_webui-0.0.4.dist-info/entry_points.txt
bms_webui-0.0.4.dist-info/top_level.txt
bms_webui-0.0.4.dist-info/RECORD
